navicat_spock/__init__.py
navicat_spock/__main__.py
navicat_spock/exceptions.py
navicat_spock/helpers.py
navicat_spock/piecewise_regression.py
navicat_spock/plotting2d.py
navicat_spock/spock.py
navicat_spock-0.0.4.dist-info/LICENSE
navicat_spock-0.0.4.dist-info/METADATA
navicat_spock-0.0.4.dist-info/WHEEL
navicat_spock-0.0.4.dist-info/entry_points.txt
navicat_spock-0.0.4.dist-info/top_level.txt
navicat_spock-0.0.4.dist-info/RECORD
