Metadata-Version: 2.1
Name: navicat-spock
Version: 0.0.4
Summary: Volcano Plot fitting tool
Home-page: https://github.com/rlaplaza/spock
Author: rlaplaza, lcmd-epfl, ace-ethz, dcl-ethz
Author-email: "R. Laplaza" <rlaplaza@duck.com>
Keywords: compchem
Classifier: Programming Language :: Python :: 3
Classifier: License :: OSI Approved :: MIT License
Classifier: Operating System :: OS Independent
Requires-Python: >=3.8
License-File: LICENSE
Requires-Dist: matplotlib>=3.6.1
Requires-Dist: piecewise-regression>=1.5
Requires-Dist: scikit-learn>=1.2.0
Requires-Dist: numpy>=1.23.4
Requires-Dist: pandas>=1.5.0
Requires-Dist: setuptools>=65.4.1
Requires-Dist: statsmodels>=0.14.1
Requires-Dist: scipy==1.10.1
